sped_ecf/__init__.py
sped_ecf/layout2/__init__.py
sped_ecf/layout2/arquivos.py
sped_ecf/layout2/blocos.py
sped_ecf/layout2/registros.py
sped_ecf/layout3/__init__.py
sped_ecf/layout3/arquivos.py
sped_ecf/layout3/blocos.py
sped_ecf/layout3/registros.py
sped_ecf/leiaute2/__init__.py
sped_ecf/leiaute2/arquivos.py
sped_ecf/leiaute2/blocos.py
sped_ecf/leiaute2/registros.py
sped_ecf/leiaute3/__init__.py
sped_ecf/leiaute3/arquivos.py
sped_ecf/leiaute3/blocos.py
sped_ecf/leiaute3/registros.py
sped_ecf-0.0.1.dist-info/DESCRIPTION.rst
sped_ecf-0.0.1.dist-info/METADATA
sped_ecf-0.0.1.dist-info/RECORD
sped_ecf-0.0.1.dist-info/WHEEL
sped_ecf-0.0.1.dist-info/metadata.json
sped_ecf-0.0.1.dist-info/top_level.txt
